<?xml version="1.0" encoding="UTF-8"?>

<root-container name="fascicolazioneGestioneCambioTipi" width="1359" height="405">
  <node name="start-state1" x="25" y="160" width="132" height="36">
    <edge>
      <label x="5" y="-10"/>
    </edge>
  </node>
  <node name="new fascicolo?" x="175" y="162" width="132" height="36">
    <edge>
      <label x="-12" y="19"/>
    </edge>
    <edge>
      <label x="5" y="-10"/>
      <bendpoint w1="53" h1="-140" w2="-679" h2="-142"/>
      <bendpoint w1="820" h1="-140" w2="-80" h2="-144"/>
    </edge>
  </node>
  <node name="type change popup" x="540" y="160" width="132" height="36">
    <edge>
      <label x="5" y="-10"/>
    </edge>
  </node>
  <node name="button popup pressed?" x="695" y="163" width="132" height="36">
    <edge>
      <label x="5" y="-10"/>
    </edge>
    <edge>
      <label x="5" y="-10"/>
    </edge>
  </node>
  <node name="update fields" x="883" y="106" width="132" height="36">
    <edge>
      <label x="5" y="-10"/>
    </edge>
  </node>
  <node name="revert type" x="894" y="207" width="132" height="36">
    <edge>
      <label x="5" y="-10"/>
    </edge>
  </node>
  <node name="collector" x="1075" y="166" width="132" height="36">
    <edge>
      <label x="5" y="-10"/>
    </edge>
  </node>
  <node name="end-state1" x="1226" y="163" width="132" height="36"/>
  <node name="type changed?" x="362" y="159" width="132" height="36">
    <edge>
      <label x="-9" y="-17"/>
    </edge>
    <edge>
      <label x="5" y="-10"/>
      <bendpoint w1="36" h1="-114" w2="-677" h2="-121"/>
      <bendpoint w1="594" h1="-113" w2="-119" h2="-120"/>
    </edge>
  </node>
</root-container>
